{
  "metadatos": {
    "ultima_actualizacion": "16/01/2026 10:14",
    "fecha_extraccion_gcgroup": "16/01/2026 10:14",
    "productos_gcgroup": 148,
    "proveedor_gcgroup": "GcGroup",
    "formula_precio_gcgroup": "(costo + 10%) + $20, redondeado a múltiplo de 5",
    "total_productos": 24
  },
  "productos": [
    {
      "nombre": "IPHONE 17 PRO 256 GB ESIM SILVER",
      "precio": 1505,
      "precio_costo": 1335.0,
      "categoria": "CELULARES IPHONE NEW",
      "proveedor": "GcGroup",
      "ganancia_porcentaje": 18,
      "extra_usd": 20,
      "fecha_actualizacion": "16/01/2026 10:14"
    },
    {
      "nombre": "IPHONE 17 PRO 512 GB ESIM ORANG/ BLUE",
      "precio": 1660,
      "precio_costo": 1475.0,
      "categoria": "CELULARES IPHONE NEW",
      "proveedor": "GcGroup",
      "ganancia_porcentaje": 18,
      "extra_usd": 20,
      "fecha_actualizacion": "16/01/2026 10:14"
    },
    {
      "nombre": "IPHONE 17 PRO 512 GB ESIM SILVER",
      "precio": 1680,
      "precio_costo": 1495.0,
      "categoria": "CELULARES IPHONE NEW",
      "proveedor": "GcGroup",
      "ganancia_porcentaje": 18,
      "extra_usd": 20,
      "fecha_actualizacion": "16/01/2026 10:14"
    },
    {
      "nombre": "IPHONE 17 PRO MAX 256 GB ESIM ORANGE",
      "precio": 1615,
      "precio_costo": 1435.0,
      "categoria": "CELULARES IPHONE NEW",
      "proveedor": "GcGroup",
      "ganancia_porcentaje": 18,
      "extra_usd": 20,
      "fecha_actualizacion": "16/01/2026 10:14"
    },
    {
      "nombre": "IPHONE 17 PRO MAX 256 GB ESIM BLUE",
      "precio": 1625,
      "precio_costo": 1445.0,
      "categoria": "CELULARES IPHONE NEW",
      "proveedor": "GcGroup",
      "ganancia_porcentaje": 18,
      "extra_usd": 20,
      "fecha_actualizacion": "16/01/2026 10:14"
    },
    {
      "nombre": "IPHONE 17 PRO MAX 256 GB ESIM SILVER",
      "precio": 1670,
      "precio_costo": 1485.0,
      "categoria": "CELULARES IPHONE NEW",
      "proveedor": "GcGroup",
      "ganancia_porcentaje": 18,
      "extra_usd": 20,
      "fecha_actualizacion": "16/01/2026 10:14"
    },
    {
      "nombre": "SAMSUNG A17 4/128 GB",
      "precio": 215,
      "precio_costo": 175.0,
      "categoria": "CELULARES SAMSUNG",
      "proveedor": "GcGroup",
      "ganancia_porcentaje": 18,
      "extra_usd": 20,
      "fecha_actualizacion": "16/01/2026 10:14"
    },
    {
      "nombre": "SAMSUNG A56 5G 8/256 GB",
      "precio": 410,
      "precio_costo": 350.0,
      "categoria": "CELULARES SAMSUNG",
      "proveedor": "GcGroup",
      "ganancia_porcentaje": 18,
      "extra_usd": 20,
      "fecha_actualizacion": "16/01/2026 10:14"
    },
    {
      "nombre": "SAMSUNG A56 5G 12/256 GB",
      "precio": 430,
      "precio_costo": 370.0,
      "categoria": "CELULARES SAMSUNG",
      "proveedor": "GcGroup",
      "ganancia_porcentaje": 18,
      "extra_usd": 20,
      "fecha_actualizacion": "16/01/2026 10:14"
    },
    {
      "nombre": "SAMSUNG S25 12/256 GB",
      "precio": 780,
      "precio_costo": 685.0,
      "categoria": "CELULARES SAMSUNG",
      "proveedor": "GcGroup",
      "ganancia_porcentaje": 18,
      "extra_usd": 20,
      "fecha_actualizacion": "16/01/2026 10:14"
    },
    {
      "nombre": "SAMSUNG S25 FE 8/256 GB",
      "precio": 690,
      "precio_costo": 605.0,
      "categoria": "CELULARES SAMSUNG",
      "proveedor": "GcGroup",
      "ganancia_porcentaje": 18,
      "extra_usd": 20,
      "fecha_actualizacion": "16/01/2026 10:14"
    },
    {
      "nombre": "MOTOROLA E15 2/64 GB",
      "precio": 110,
      "precio_costo": 80.0,
      "categoria": "CELULARES MOTOROLA",
      "proveedor": "GcGroup",
      "ganancia_porcentaje": 18,
      "extra_usd": 20,
      "fecha_actualizacion": "16/01/2026 10:14"
    },
    {
      "nombre": "MOTOROLA G04 4/128 GB",
      "precio": 150,
      "precio_costo": 115.0,
      "categoria": "CELULARES MOTOROLA",
      "proveedor": "GcGroup",
      "ganancia_porcentaje": 18,
      "extra_usd": 20,
      "fecha_actualizacion": "16/01/2026 10:14"
    },
    {
      "nombre": "XIAOMI 14T 5G 12/512 GB",
      "precio": 560,
      "precio_costo": 485.0,
      "categoria": "CELULARES XIAOMI",
      "proveedor": "GcGroup",
      "ganancia_porcentaje": 18,
      "extra_usd": 20,
      "fecha_actualizacion": "16/01/2026 10:14"
    },
    {
      "nombre": "JBL XTREME 4 100 WATTS 24 HORAS NEGRO",
      "precio": 315,
      "precio_costo": 265.0,
      "categoria": "JBL PARLANTES/AURICULARES",
      "proveedor": "GcGroup",
      "ganancia_porcentaje": 18,
      "extra_usd": 20,
      "fecha_actualizacion": "16/01/2026 10:14"
    },
    {
      "nombre": "JBL BOOMBOX 4 210 WATTS 2V CAMUFLADO",
      "precio": 575,
      "precio_costo": 500.0,
      "categoria": "JBL PARLANTES/AURICULARES",
      "proveedor": "GcGroup",
      "ganancia_porcentaje": 18,
      "extra_usd": 20,
      "fecha_actualizacion": "16/01/2026 10:14"
    },
    {
      "nombre": "PS5 C/LECTORA 1TB RETURNAL + RATCHET",
      "precio": 655,
      "precio_costo": 570.0,
      "categoria": "VIDEO JUEGOS",
      "proveedor": "GcGroup",
      "ganancia_porcentaje": 18,
      "extra_usd": 20,
      "fecha_actualizacion": "16/01/2026 10:14"
    },
    {
      "nombre": "IPAD 11 A16 128 GB",
      "precio": 510,
      "precio_costo": 440.0,
      "categoria": "IPAD",
      "proveedor": "GcGroup",
      "ganancia_porcentaje": 18,
      "extra_usd": 20,
      "fecha_actualizacion": "16/01/2026 10:14"
    },
    {
      "nombre": "IPAD 11 A16 256 GB",
      "precio": 630,
      "precio_costo": 550.0,
      "categoria": "IPAD",
      "proveedor": "GcGroup",
      "ganancia_porcentaje": 18,
      "extra_usd": 20,
      "fecha_actualizacion": "16/01/2026 10:14"
    },
    {
      "nombre": "IPAD AIR 11” M3 256 GB",
      "precio": 840,
      "precio_costo": 740.0,
      "categoria": "IPAD",
      "proveedor": "GcGroup",
      "ganancia_porcentaje": 18,
      "extra_usd": 20,
      "fecha_actualizacion": "16/01/2026 10:14"
    },
    {
      "nombre": "100” Smart TV Xiaomi Max 4K 144HZ",
      "precio": 3110,
      "precio_costo": 2780.0,
      "categoria": "TELEVISORES",
      "proveedor": "GcGroup",
      "ganancia_porcentaje": 18,
      "extra_usd": 20,
      "fecha_actualizacion": "16/01/2026 10:14"
    },
    {
      "nombre": "98” Smart TV TCL 4K UHD QLED 98P8K",
      "precio": 3240,
      "precio_costo": 2900.0,
      "categoria": "TELEVISORES",
      "proveedor": "GcGroup",
      "ganancia_porcentaje": 18,
      "extra_usd": 20,
      "fecha_actualizacion": "16/01/2026 10:14"
    },
    {
      "nombre": "60” Smart TV 4K UHD Admiral AD60G3FN",
      "precio": 485,
      "precio_costo": 420.0,
      "categoria": "TELEVISORES",
      "proveedor": "GcGroup",
      "ganancia_porcentaje": 18,
      "extra_usd": 20,
      "fecha_actualizacion": "16/01/2026 10:14"
    },
    {
      "nombre": "32” Smart Philco / Admiral",
      "precio": 200,
      "precio_costo": 160.0,
      "categoria": "TELEVISORES",
      "proveedor": "GcGroup",
      "ganancia_porcentaje": 18,
      "extra_usd": 20,
      "fecha_actualizacion": "16/01/2026 10:14"
    }
  ]
}